cute.py
cute/__init__.py
cute/cute.py
idacute-1.0.1.dist-info/DESCRIPTION.rst
idacute-1.0.1.dist-info/METADATA
idacute-1.0.1.dist-info/RECORD
idacute-1.0.1.dist-info/WHEEL
idacute-1.0.1.dist-info/metadata.json
idacute-1.0.1.dist-info/top_level.txt
