Metadata-Version: 2.0
Name: idacute
Version: 1.0.1
Summary: Cross-Qt compatibility module for IDAPython
Home-page: https://github.com/tmr232/Cute
Author: Tamir Bahar
Author-email: UNKNOWN
License: MIT
Platform: UNKNOWN
